LICENSE
README.md
lyynetwork.py
setup.py
lyynetwork.egg-info/PKG-INFO
lyynetwork.egg-info/SOURCES.txt
lyynetwork.egg-info/dependency_links.txt
lyynetwork.egg-info/top_level.txt