Metadata-Version: 2.1
Name: lyynetwork
Version: 1.1
Summary: network application for  lyy
Author: lyy
Author-email: 
License: MIT
License-File: LICENSE
